Workbook

Sheet Summary
A1: Takasbank on-prem EDW - ETL tool comparison
A2: ODI, Informatica PowerCenter, dbt, Cloudera Data Platform, Apache Spark | as of 2026-10-14
A4: Recommendation
A5: 1. Select Oracle Data Integrator 14c as the enterprise ELT platform: pushdown into the existing Exadata, PL/SQL-friendly, supported to 2030/2033.
A6: 2. Serve near-real-time operational ('izleme') reports from the Kale Active Data Guard read-only standby, not from an ETL tool.
A7: 3. Use GoldenGate (via ODI JKM) only for data products whose S0 SLA is proven, after the licence question is settled.
A8: 4. Keep dbt-core + dbt-oracle as the qualified alternative and procurement-free fallback; run the PoC head-to-head ODI vs dbt.
A9: 5. Exclude PowerCenter (fails support-horizon gate; successor needs a cloud control plane). Do not build the core DWH on Cloudera or Spark.
A11: Metric | B11: ODI | C11: PowerCenter | D11: dbt | E11: CDP | F11: Spark
A12: Weighted total (base) | B12: ='Scoring Matrix'!C17 | C12: ='Scoring Matrix'!D17 | D12: ='Scoring Matrix'!E17 | E12: ='Scoring Matrix'!F17 | F12: ='Scoring Matrix'!G17
A13: Rank (base) | B13: ='Scoring Matrix'!C18 | C13: ='Scoring Matrix'!D18 | D13: ='Scoring Matrix'!E18 | E13: ='Scoring Matrix'!F18 | F13: ='Scoring Matrix'!G18
A14: Knock-out gates | B14: =Gates!C8 | C14: =Gates!D8 | D14: =Gates!E8 | E14: =Gates!F8 | F14: =Gates!G8
A15: Average use-case fit (1-5) | B15: ='Use-Case Fit'!D12 | C15: ='Use-Case Fit'!E12 | D15: ='Use-Case Fit'!F12 | E15: ='Use-Case Fit'!G12 | F15: ='Use-Case Fit'!H12
A16: 5-year TCO band | B16: ='TCO Drivers'!B11 | C16: ='TCO Drivers'!C11 | D16: ='TCO Drivers'!D11 | E16: ='TCO Drivers'!E11 | F16: ='TCO Drivers'!F11
A17: Weighted total (Oracle-team-first) | B17: =Sensitivity!B6 | C17: =Sensitivity!C6 | D17: =Sensitivity!D6 | E17: =Sensitivity!E6 | F17: =Sensitivity!F6
A18: Weighted total (Real-time-first) | B18: =Sensitivity!B7 | C18: =Sensitivity!C7 | D18: =Sensitivity!D7 | E18: =Sensitivity!E7 | F18: =Sensitivity!F7
A19: Weighted total (Cost-first) | B19: =Sensitivity!B8 | C19: =Sensitivity!C8 | D19: =Sensitivity!D8 | E19: =Sensitivity!E8 | F19: =Sensitivity!F8
A21: How to use this workbook
A22: - Yellow cells are inputs: weights on 'Criteria & Weights', scores on 'Scoring Matrix' and 'Use-Case Fit', PoC results on 'PoC Plan'.
A23: - All totals, ranks, gate outcomes and scenario winners are formulas and recalculate on change.
A24: - The tools are not like-for-like (suite vs framework vs platform vs engine); each is scored as a deployable stack with its CDC/orchestration companions.
A25: - Vault note: Obsidian Vault/Kendi Notlarım/ETL Araç Karşılaştırması - Ekim 2026.md. Source of numbers: comparison_data.py.

Sheet Criteria & Weights
A1: Evaluation criteria and weights
A2: Yellow cells are inputs. Base weights drive the Scoring Matrix; scenario weights drive the Sensitivity sheet. Each column must sum to 100.
A4: # | B4: Criterion | C4: What good looks like at Takasbank | D4: Base (Takasbank profile) | E4: Oracle-team-first | F4: Real-time-first | G4: Cost-first
A5: 1 | B5: Exadata / Oracle pushdown and performance | C5: Runs set-based work inside Exadata (Smart Scan, HCC, parallel DML), handles 2B-row SWIFT and 20M/day takas volumes without a second compute tier. | D5: 14 | E5: 16 | F5: 10 | G5: 12
A6: 2 | B6: Real-time, CDC and operational reporting | C6: Supports S0 near-real-time and S1 micro-batch for izleme screens and intraday Fon Bilgilendirme without touching prod Kale. | D6: 12 | E6: 8 | F6: 24 | G6: 8
A7: 3 | B7: Security, on-prem and regulatory compliance | C7: Fully on-prem with no external control plane; BDDK/KVKK/SPK fit; TDE/VPD/redaction respected; security patches through the horizon. | D7: 10 | E7: 10 | F7: 10 | G7: 10
A8: 4 | B8: Governance: lineage, metadata, audit, data quality | C8: Column-level source-to-report lineage, run lineage, audit trail and data-quality rules for regulatory reports. | D8: 10 | E8: 8 | F8: 8 | G8: 8
A9: 5 | B9: Team skill fit and learning curve | C9: Usable by an Oracle DBA / PL/SQL team with no DWH/ETL background; hiring market in Turkey. | D9: 10 | E9: 16 | F9: 8 | G9: 10
A10: 6 | B10: Source connectivity | C10: Kale standby, ARSIV, CekDB, BIST Replica BIDB / Borsa DWH, FTP/CSV, EPIAS web services, possible Postgres/MSSQL. | D10: 8 | E10: 6 | F10: 10 | G10: 6
A11: 7 | B11: Transformation and modelling | C11: SCD2, bitemporal core, incremental merge, set-based logic, reuse of existing PL/SQL. | D11: 8 | E11: 8 | F11: 6 | G11: 8
A12: 8 | B12: 5-year total cost of ownership | C12: Licence + support + infrastructure + people over five years (higher score = lower cost). | D12: 8 | E12: 8 | F12: 6 | G12: 22
A13: 9 | B13: Operations and orchestration | C13: Automic integration, gün sonu event triggering, restart from failure, monitoring, without a 24/7 team. | D13: 7 | E13: 8 | F13: 8 | G13: 6
A14: 10 | B14: DevOps: Git, CI/CD, automated tests | C14: Version control, code review, automated tests and promotion DEV -> TEST -> PREPROD -> PROD. | D14: 6 | E14: 6 | F14: 4 | G14: 5
A15: 11 | B15: Vendor viability, roadmap and local support | C15: Supported release horizon, roadmap risk, ownership changes, partners in Turkey. | D15: 7 | E15: 6 | F15: 6 | G15: 5
B16: Total (must be 100) | D16: =SUM(D5:D15) | E16: =SUM(E5:E15) | F16: =SUM(F5:F15) | G16: =SUM(G5:G15)

Sheet Scoring Matrix
A1: Weighted scoring matrix (scores 1-5, base weights)
A2: Each tool is scored as a deployable stack incl. required CDC/orchestration companions. Weighted total = SUMPRODUCT(weights, scores) / 5, so 100 = perfect.
A4: Criterion | B4: Weight | C4: ODI | D4: PowerCenter | E4: dbt | F4: CDP | G4: Spark
A5: Exadata / Oracle pushdown and performance | B5: ='Criteria & Weights'!D5 | C5: 5 | D5: 3 | E5: 5 | F5: 2 | G5: 2
A6: Real-time, CDC and operational reporting | B6: ='Criteria & Weights'!D6 | C6: 3 | D6: 3 | E6: 2 | F6: 4 | G6: 4
A7: Security, on-prem and regulatory compliance | B7: ='Criteria & Weights'!D7 | C7: 4 | D7: 2 | E7: 4 | F7: 4 | G7: 2
A8: Governance: lineage, metadata, audit, data quality | B8: ='Criteria & Weights'!D8 | C8: 4 | D8: 4 | E8: 3 | F8: 4 | G8: 2
A9: Team skill fit and learning curve | B9: ='Criteria & Weights'!D9 | C9: 4 | D9: 3 | E9: 4 | F9: 1 | G9: 1
A10: Source connectivity | B10: ='Criteria & Weights'!D10 | C10: 4 | D10: 5 | E10: 1 | F10: 5 | G10: 3
A11: Transformation and modelling | B11: ='Criteria & Weights'!D11 | C11: 4 | D11: 4 | E11: 4 | F11: 3 | G11: 3
A12: 5-year total cost of ownership | B12: ='Criteria & Weights'!D12 | C12: 3 | D12: 2 | E12: 5 | F12: 1 | G12: 2
A13: Operations and orchestration | B13: ='Criteria & Weights'!D13 | C13: 4 | D13: 4 | E13: 3 | F13: 2 | G13: 1
A14: DevOps: Git, CI/CD, automated tests | B14: ='Criteria & Weights'!D14 | C14: 3 | D14: 2 | E14: 5 | F14: 3 | G14: 4
A15: Vendor viability, roadmap and local support | B15: ='Criteria & Weights'!D15 | C15: 4 | D15: 1 | E15: 2 | F15: 4 | G15: 2
A17: Weighted total (0-100) | C17: =ROUND(SUMPRODUCT($B$5:$B$15,C5:C15)/5,1) | D17: =ROUND(SUMPRODUCT($B$5:$B$15,D5:D15)/5,1) | E17: =ROUND(SUMPRODUCT($B$5:$B$15,E5:E15)/5,1) | F17: =ROUND(SUMPRODUCT($B$5:$B$15,F5:F15)/5,1) | G17: =ROUND(SUMPRODUCT($B$5:$B$15,G5:G15)/5,1)
A18: Rank | C18: =RANK(C17,$C$17:$G$17) | D18: =RANK(D17,$C$17:$G$17) | E18: =RANK(E17,$C$17:$G$17) | F18: =RANK(F17,$C$17:$G$17) | G18: =RANK(G17,$C$17:$G$17)
A19: Knock-out gate status (see Gates) | C19: =Gates!C8 | D19: =Gates!D8 | E19: =Gates!E8 | F19: =Gates!F8 | G19: =Gates!G8
A21: Scoring rationale
A22: Criterion | B22: Weight | C22: ODI | D22: PowerCenter | E22: dbt | F22: CDP | G22: Spark
A23: Exadata / Oracle pushdown and performance | B23: 14 | C23: 5 - E-LT by design: generated SQL runs in the target Exadata; Oracle KMs use external tables, parallel DML, MERGE and partition exchange. | D23: 3 - Engine-based ETL; Pushdown Optimization (extra option) can push to Oracle, but an ETL server tier remains. | E23: 5 - Every model compiles to SQL executed in Exadata; incremental merge and microbatch strategies supported by dbt-oracle. | F23: 2 - Processing happens on the Cloudera cluster; Oracle is reached via JDBC/Sqoop-style pulls and results written back for MSTR. | G23: 2 - Reads and writes Oracle through JDBC; no use of Smart Scan; 2B-row SWIFT reload is the worst case.
A24: Real-time, CDC and operational reporting | B24: 12 | C24: 3 - Batch and micro-batch natively; S0 only via GoldenGate JKM (separate licence, DBA concerns). ADG standby covers raw izleme screens. | D24: 3 - PowerExchange CDC for Oracle (separate licence) gives log-based capture; real-time option exists. | E24: 2 - No CDC or streaming; microbatch runs give S1 at best; S0 must come from ADG or GoldenGate. | F24: 4 - Kafka + Flink + NiFi give true streaming; Oracle CDC still needs Debezium/LogMiner or GoldenGate on Kale side. | G24: 4 - Structured Streaming and 4.x Real-time Mode with Kafka + Debezium; parts still experimental.
A25: Security, on-prem and regulatory compliance | B25: 10 | C25: 4 - Fully on-prem; agents run inside the bank; credentials in the ODI repository/wallet; relies on Oracle DB security (TDE, VPD). | D25: 2 - On-prem today, but security fixes stop after Extended Support (Mar 2027); successor needs an internet-connected Secure Agent and cloud control plane. | E25: 4 - Self-hosted Core sends no data out; runs with DB accounts; secrets handled by the runner. Do not use dbt platform (SaaS). | F25: 4 - On-prem with Kerberos, Ranger, TLS; larger attack surface and second security perimeter. | G25: 2 - Everything (Kerberos/TLS, secrets, authorisation) is self-built and self-patched.
A26: Governance: lineage, metadata, audit, data quality | B26: 10 | C26: 4 - Repository holds mappings, column lineage and impact analysis; run history per session. DQ needs custom checks or Oracle EDQ. | D26: 4 - Metadata Manager lineage and mature audit; DQ via separate Informatica products. | E26: 3 - DAG lineage, docs site and built-in tests; column-level lineage only in the SaaS platform; run artifacts must be harvested. | F26: 4 - Atlas lineage and Ranger audit across the cluster; lineage breaks at the Oracle boundary. | G26: 2 - Lineage via OpenLineage/DIY; no built-in catalogue or audit.
A27: Team skill fit and learning curve | B27: 10 | C27: 4 - SQL-centric; PL/SQL developers become productive quickly. GUI and KM concepts need training. | D27: 3 - No in-house ETL skills; PowerCenter developers available in the Turkish market (MKK). | E27: 4 - SQL first; Jinja macros, YAML and Git are new but small steps for SQL people. | F27: 1 - Hadoop, Kafka, Flink, Spark, Kerberos skills absent; scarce and expensive hires. | G27: 1 - Python/Scala distributed-systems engineering; furthest from the PL/SQL team.
A28: Source connectivity | B28: 8 | C28: 4 - Oracle, JDBC (Postgres/MSSQL), files, FTP, web-service tools; BIDB pull from Borsa DWH as Ondata described. | D28: 5 - Broadest connector catalogue of the five: files, FTP, web services, all RDBMS, mainframe. | E28: 1 - None: dbt only transforms what is already in the database; landing must be built separately. | F28: 5 - NiFi plus Kafka Connect cover files, FTP, web services, APIs and all databases. | G28: 3 - JDBC and files are fine; FTP/web services need custom code.
A29: Transformation and modelling | B29: 8 | C29: 4 - Built-in SCD2 and incremental IKMs; bitemporal patterns via custom KM; existing procedure SQL reusable. | D29: 4 - Rich transformation library, SCD wizards, lookups; logic lives in the engine, not in SQL. | E29: 4 - Snapshots (SCD2), incremental models, tests, macros; bitemporal handled with custom macros. | F29: 3 - Spark SQL / Hive / Iceberg MERGE are capable, but the integrated core would be split between two platforms. | G29: 3 - Unlimited logic, but core tables live in Oracle, so every load is a cross-system write.
A30: 5-year total cost of ownership | B30: 8 | C30: 3 - Processor licences on agent hosts plus 22% annual support; HA adds WebLogic/Coherence. No extra compute (Exadata). | D30: 2 - Quote-based licence, extended-support premium, and a forced migration to IDMC within the 5-year window. | E30: 5 - No licence; people cost for building the ingestion/orchestration framework. | F30: 1 - CCU + data-under-management subscription, a new server cluster, and a platform team on top of Exadata. | G30: 2 - No licence, but cluster hardware plus 3-5 platform/data engineers.
A31: Operations and orchestration | B31: 7 | C31: 4 - Load plans with restart, agent HA, Automic triggers scenarios via command line or web service. | D31: 4 - Workflow Manager/Monitor, restart and recovery are mature. | E31: 3 - CLI runs from Automic; `dbt retry` for restarts; monitoring built from run_results artifacts. | F31: 2 - Cloudera Manager helps, but a multi-service cluster needs 24/7 operations Takasbank lacks. | G31: 1 - Scheduler, monitoring, restart and upgrades are all DIY.
A32: DevOps: Git, CI/CD, automated tests | B32: 6 | C32: 3 - VCS/Git integration and deployment archives exist, but branching and merging repository objects is clumsy. | D32: 2 - Repository-centric; XML export for Git; weak CI/CD. | E32: 5 - Best-in-class: Git, pull requests, CI, environment targets, slim CI. | F32: 3 - Code-based jobs are Git-friendly; platform configuration is not. | G32: 4 - Code-first and testable; CI/CD must be assembled.
A33: Vendor viability, roadmap and local support | B33: 7 | C33: 4 - Oracle; 14c supported to 2030/2033; Borsa Istanbul reference; local integrators. | D33: 1 - On-prem product at end of standard support; now part of Salesforce; partner reported no new on-prem sales. | E33: 2 - Open source with no on-prem SLA; Oracle adapter community/Oracle-maintained and not yet on v2 engine; vendor focus is cloud. | F33: 4 - 7.3.2 LTS supported to 2032; established vendor with Turkish banking references. | G33: 2 - Community project; support only via third parties; fast release cadence to track.

Sheet Gates
A1: Knock-out gates (pass / conditional / fail before scoring)
A2: A Fail removes the tool from the shortlist regardless of its weighted score. Conditional = passes only with the stated mitigation.
A4: Gate | B4: Requirement | C4: ODI | D4: PowerCenter | E4: dbt | F4: CDP | G4: Spark
A5: G1 | B5: Runs fully on-prem with no external control plane or internet-connected agent | C5: Pass | D5: Conditional | E5: Pass | F5: Pass | G5: Pass
A6: G2 | B6: Vendor-supported release with security fixes for 5+ years (to late 2031) | C6: Pass | D6: Fail | E6: Conditional | F6: Pass | G6: Conditional
A7: G3 | B7: Production-grade support for Oracle Database 19c/23ai on Exadata | C7: Pass | D7: Pass | E7: Pass | F7: Pass | G7: Pass
B8: Overall | C8: =IF(COUNTIF(C5:C7,"Fail")>0,"Fail",IF(COUNTIF(C5:C7,"Conditional")>0,"Conditional","Pass")) | D8: =IF(COUNTIF(D5:D7,"Fail")>0,"Fail",IF(COUNTIF(D5:D7,"Conditional")>0,"Conditional","Pass")) | E8: =IF(COUNTIF(E5:E7,"Fail")>0,"Fail",IF(COUNTIF(E5:E7,"Conditional")>0,"Conditional","Pass")) | F8: =IF(COUNTIF(F5:F7,"Fail")>0,"Fail",IF(COUNTIF(F5:F7,"Conditional")>0,"Conditional","Pass")) | G8: =IF(COUNTIF(G5:G7,"Fail")>0,"Fail",IF(COUNTIF(G5:G7,"Conditional")>0,"Conditional","Pass"))
A10: Gate evidence
A11: Gate | B11: Requirement | C11: ODI | D11: PowerCenter | E11: dbt | F11: CDP | G11: Spark
A12: G1 | B12: Runs fully on-prem with no external control plane or internet-connected agent | C12: Pass: All components inside the bank. | D12: Conditional: 10.5 yes; the only supported successor (CDI-PC/IDMC) needs a cloud control plane. | E12: Pass: dbt-core only; dbt platform (SaaS) excluded. | F12: Pass: Cloudera Base on premises. | G12: Pass: Self-managed.
A13: G2 | B13: Vendor-supported release with security fixes for 5+ years (to late 2031) | C13: Pass: 14c Premier to Dec 2030, Extended to Dec 2033. | D13: Fail: Standard support ended Mar 2026; Extended to Mar 2027; Sustaining to 2029 without new fixes. | E13: Conditional: Apache 2.0 with indefinite OSS commitment, but no SLA; each minor line supported 1 year. | F13: Pass: 7.3.2 LTS to Mar 2032. | G13: Conditional: Community maintenance only; third-party support needed.
A14: G3 | B14: Production-grade support for Oracle Database 19c/23ai on Exadata | C14: Pass: Native Oracle KMs, Exadata-aware loading. | D14: Pass: Certified Oracle connectivity. | E14: Pass: dbt-oracle supports on-prem Oracle via python-oracledb. | F14: Pass: JDBC source/target. | G14: Pass: JDBC source/target.

Sheet Sensitivity
A1: Sensitivity: weighted totals under alternative weightings
A2: Totals are live formulas over 'Criteria & Weights' scenario columns and 'Scoring Matrix' scores.
A4: Scenario | B4: ODI | C4: PowerCenter | D4: dbt | E4: CDP | F4: Spark | G4: Winner
A5: Base (Takasbank profile) | B5: =ROUND(SUMPRODUCT('Criteria & Weights'!$D$5:$D$15,'Scoring Matrix'!C$5:C$15)/5,1) | C5: =ROUND(SUMPRODUCT('Criteria & Weights'!$D$5:$D$15,'Scoring Matrix'!D$5:D$15)/5,1) | D5: =ROUND(SUMPRODUCT('Criteria & Weights'!$D$5:$D$15,'Scoring Matrix'!E$5:E$15)/5,1) | E5: =ROUND(SUMPRODUCT('Criteria & Weights'!$D$5:$D$15,'Scoring Matrix'!F$5:F$15)/5,1) | F5: =ROUND(SUMPRODUCT('Criteria & Weights'!$D$5:$D$15,'Scoring Matrix'!G$5:G$15)/5,1) | G5: =INDEX($B$4:$F$4,MATCH(MAX(B5:F5),B5:F5,0))
A6: Oracle-team-first | B6: =ROUND(SUMPRODUCT('Criteria & Weights'!$E$5:$E$15,'Scoring Matrix'!C$5:C$15)/5,1) | C6: =ROUND(SUMPRODUCT('Criteria & Weights'!$E$5:$E$15,'Scoring Matrix'!D$5:D$15)/5,1) | D6: =ROUND(SUMPRODUCT('Criteria & Weights'!$E$5:$E$15,'Scoring Matrix'!E$5:E$15)/5,1) | E6: =ROUND(SUMPRODUCT('Criteria & Weights'!$E$5:$E$15,'Scoring Matrix'!F$5:F$15)/5,1) | F6: =ROUND(SUMPRODUCT('Criteria & Weights'!$E$5:$E$15,'Scoring Matrix'!G$5:G$15)/5,1) | G6: =INDEX($B$4:$F$4,MATCH(MAX(B6:F6),B6:F6,0))
A7: Real-time-first | B7: =ROUND(SUMPRODUCT('Criteria & Weights'!$F$5:$F$15,'Scoring Matrix'!C$5:C$15)/5,1) | C7: =ROUND(SUMPRODUCT('Criteria & Weights'!$F$5:$F$15,'Scoring Matrix'!D$5:D$15)/5,1) | D7: =ROUND(SUMPRODUCT('Criteria & Weights'!$F$5:$F$15,'Scoring Matrix'!E$5:E$15)/5,1) | E7: =ROUND(SUMPRODUCT('Criteria & Weights'!$F$5:$F$15,'Scoring Matrix'!F$5:F$15)/5,1) | F7: =ROUND(SUMPRODUCT('Criteria & Weights'!$F$5:$F$15,'Scoring Matrix'!G$5:G$15)/5,1) | G7: =INDEX($B$4:$F$4,MATCH(MAX(B7:F7),B7:F7,0))
A8: Cost-first | B8: =ROUND(SUMPRODUCT('Criteria & Weights'!$G$5:$G$15,'Scoring Matrix'!C$5:C$15)/5,1) | C8: =ROUND(SUMPRODUCT('Criteria & Weights'!$G$5:$G$15,'Scoring Matrix'!D$5:D$15)/5,1) | D8: =ROUND(SUMPRODUCT('Criteria & Weights'!$G$5:$G$15,'Scoring Matrix'!E$5:E$15)/5,1) | E8: =ROUND(SUMPRODUCT('Criteria & Weights'!$G$5:$G$15,'Scoring Matrix'!F$5:F$15)/5,1) | F8: =ROUND(SUMPRODUCT('Criteria & Weights'!$G$5:$G$15,'Scoring Matrix'!G$5:G$15)/5,1) | G8: =INDEX($B$4:$F$4,MATCH(MAX(B8:F8),B8:F8,0))
A10: Reading: ODI leads in the base, Oracle-team-first and real-time-first scenarios; dbt overtakes ODI only when TCO is weighted at 22%. PowerCenter's total is irrelevant because it fails gate G2.

Sheet Capability Detail
A1: Tool profiles
A2: Vendor facts verified 2026-10-14; see Sources.
A4: Attribute | B4: Oracle Data Integrator | C4: Informatica PowerCenter | D4: dbt (dbt-core + dbt-oracle) | E4: Cloudera Data Platform (Base on premises) | F4: Apache Spark (self-managed)
A5: Product / version | B5: ODI 14c (14.1.2.0.0) | C5: PowerCenter 10.5.x (final on-prem line) | D5: dbt-core 1.12 + dbt-oracle 1.12 (dbt v2/Fusion has no Oracle adapter yet) | E5: Cloudera Base on premises 7.3.2 LTS + Cloudera Streaming (Kafka, Flink) + Flow Management (NiFi) | F5: Apache Spark 4.2.0 (Jul 2026) on Kubernetes/YARN
A6: Category | B6: ELT suite (pushdown, E-LT) | C6: ETL engine suite | D6: In-warehouse SQL transformation framework | E6: Big-data platform (storage + compute + streaming) | F6: Distributed processing engine
A7: Deployable stack evaluated | B7: ODI 14c agents + Knowledge Modules; GoldenGate JKM only for proven S0/S1 feeds; Automic calls ODI scenarios / load plans | C7: PowerCenter Integration Service + Repository; PowerExchange CDC for Oracle (separate licence); Pushdown Optimization option | D7: dbt-core + dbt-oracle on Linux runners; ingestion by PL/SQL + external tables/SQL*Loader (or ODI); Automic runs `dbt build`; Git + CI | E7: Cloudera Base cluster (Ozone/HDFS, Iceberg, Hive/Impala, Spark), Cloudera Streaming (Kafka/Flink, Kafka Connect + Debezium), NiFi for files/web services, Atlas/Ranger (SDX) | F7: Spark 4.2 (SQL, Structured Streaming, Declarative Pipelines) + Kafka + Debezium + Airflow/Automic + Iceberg or JDBC write-back to Oracle; DIY security and lineage (OpenLineage)
A8: Licensing | B8: Per processor or Named User Plus on every host running an ODI agent (list ref. USD 30k/processor + 22% annual support). WebLogic EE + Coherence EE needed for clustered agent HA. GoldenGate licensed separately on capture/delivery hosts. | C8: Quote-based; on-prem PowerCenter no longer sold to new customers per the Informatica partner (BI Technology) - successor CDI-PC is IPU consumption-based via an internet-connected IDMC Secure Agent. | D8: Apache 2.0, no licence fee. dbt platform (SaaS) is not usable on-prem; no vendor SLA for self-hosted Core. Fivetran + dbt Labs merger completed 1 Jun 2026. | E8: Subscription by Cloudera Compute Units (cores/6 + RAM GB/12) plus Data Under Management since Feb 2025; quote-based. Requires its own commodity-server cluster - cannot run on Exadata. | F8: Apache 2.0, no licence fee. No vendor support unless bought from a third party.
A9: Lifecycle / support | B9: FMW 14.1.2 Premier Support to Dec 2030, Extended to Dec 2033. ODI 12c Premier ends Dec 2026, Extended Dec 2027. Next FMW release targeted 2027. | C9: Standard support ended 31 Mar 2026. Paid Extended Support to 31 Mar 2027, Sustaining Support (no new fixes / security patches) to 31 Mar 2029. Informatica acquired by Salesforce (Nov 2025). | D9: Minor releases roughly quarterly, one year of support each (1.12 critical support to Jul 2027). dbt-oracle maintained by Oracle; v2 parser does not recognise Oracle yet. | E9: 7.3.2 LTS GA Mar 2026, supported to Mar 2032. 7.3.1 EoS Dec 2026, 7.1.9 Oct 2028. | F9: Feature release roughly every 6-7 months (4.0 May 2025, 4.1 Dec 2025, 4.2 Jul 2026); maintenance releases for a limited window per line.
A10: Strengths | B10: - Generates set-based SQL that runs inside Exadata (Smart Scan, HCC, parallel DML, partition exchange) - no second compute tier - Knowledge Modules for SCD2, incremental merge, CDC and bulk load (external tables, SQL*Loader, DB link from standby) - Native GoldenGate journalizing (JKM) when a data product truly needs S0/S1 - Repository-based lineage and impact analysis; load plans with restart from failure point - Already in the Turkish capital-markets ecosystem (Borsa Istanbul uses ODI); local partners exist | C10: - Very broad connectivity (files, FTP, web services, mainframe, all major RDBMS) - Mature workflow manager, restartability and operational monitoring - Metadata Manager lineage; large pool of PowerCenter developers in Turkey (MKK uses it) - Takasbank already has an Informatica relationship (TDM for non-prod masking) | D10: - Pure SQL pushdown on Exadata - same compute advantage as ODI - Code-first: Git, pull-request review, automated tests, environments, docs site - Built-in data tests, snapshots (SCD2), incremental merge and microbatch strategies - Zero licence cost and no procurement - can start the pilot immediately | E10: - Strongest native streaming stack (Kafka, Flink, NiFi) for S0 event pipelines - SDX governance: Atlas lineage, Ranger policies, Kerberos - fully on-prem - NiFi handles FTP/CSV, EPIAS web services and API ingestion well - Scales to data sizes far beyond Takasbank's (~10 TB Kale) | F10: - Most flexible engine: Python/Scala/SQL, ML, streaming (Real-time Mode), CDC APIs in 4.2 - No licence cost; huge community - Code-first, testable, Git-native
A11: Weaknesses | B11: - GUI-centric development; Git integration exists but merge/branching is awkward compared to code-first tools - Licence follows agent hosts; HA topology adds WebLogic/Coherence licences - Real-time capability is borrowed from GoldenGate, which the DBA team distrusts and has no 24/7 cover for - 14c requires Python 3 for custom KMs (Jython deprecated) - small learning item | C11: - End-of-support product: buying it in 2026 for a 10-year DWH is buying a forced migration - Successor (CDI-PC / IDMC) puts the control plane in the cloud - conflicts with 'data and operations stay inside the bank' - Row-by-row engine by default; full pushdown to Exadata needs the PDO option and still leaves an ETL server tier - Repository-based development; weak Git/CI story | D11: - Transformation only: no extraction, file handling, web services or CDC - a landing framework must be built - Model-level lineage only in Core; column-level lineage is a dbt platform (SaaS) feature - No commercial support for on-prem Core; Oracle adapter lags the cloud-warehouse adapters - Jinja/YAML and Git workflow are new to a PL/SQL team | E11: - A second data platform beside three Exadata machines that are 77-90% free - Data must leave Exadata to be processed and come back for MSTR - double copies, double security perimeter - Hadoop/Kafka/Spark skills absent; needs a platform team and 24/7 operations - Oracle CDC still needs a log reader (Debezium LogMiner or GoldenGate) on the Kale side | F11: - Everything around the engine is DIY: scheduling, security, lineage, monitoring, upgrades - Moves data off Exadata through JDBC - the slowest path for a 2-billion-row SWIFT table - Requires Python/Scala data engineers and a platform team Takasbank does not have - Real-time Mode is still marked experimental for parts of the API
A12: Takasbank fit | B12: Best structural fit: Oracle-only estate, Exadata already paid for, PL/SQL team, Kale-centric sources, files and BIDB pulls. | C12: Fails the support-horizon gate. Only defensible as a short-term bridge for an existing PowerCenter estate - which Takasbank does not have. | D12: Strong transformation layer and the fastest start, but needs a separate, home-built ingestion and orchestration layer. | E12: Over-sized for a 10 TB Oracle-centric DWH. Revisit only for a future streaming/AI or unstructured-data mandate. | F12: Weakest fit: maximum engineering load, minimum use of existing Oracle investment.

Sheet Real-time & Latency
A1: Real-time and operational reporting by latency class (S0-S4)
A2: Score 1-5 = how well the tool stack serves the class without touching prod Kale. Recommended pattern is tool-independent.
A4: Class | B4: Meaning | C4: Takasbank example | D4: Recommended pattern | E4: ODI | F4: PowerCenter | G4: dbt | H4: CDP | I4: Spark
A5: S0 | B5: Near real-time (seconds) | C5: Izleme screens, Team Developer current-state queries | D5: Kale ADG read-only standby on sur; GoldenGate -> LND -> ODS_ projection only for products with a proven SLA | E5: 2 | F5: 3 | G5: 1 | H5: 5 | I5: 4
A6: S1 | B6: Intraday micro-batch (5-30 min) | C6: Fon Bilgilendirme 08:00-17:45 with correction files | D6: Watermark/SCN-based micro-batch from the standby into LND, recompute affected funds only | E6: 4 | F6: 4 | G6: 3 | H6: 5 | I6: 4
A7: S2 | B7: Gün sonu (T-1) | C7: BISTECH SPK 13 reports, SWIFT legal reports, takas positions | D7: SCN-consistent extract from standby after the machine-readable gün sonu event | E7: 5 | F7: 4 | G7: 5 | H7: 3 | I7: 3
A8: S3 | B8: Scheduled file / external feed | C8: FTP/CSV, EPIAS web services, Borsa DWH fund contracts, Verda file output | D8: Manifest + checksum landing; external tables for files; web-service pull into LND_FILE / LND_EPIAS | E8: 4 | F8: 5 | G8: 1 | H8: 5 | I8: 3
A9: S4 | B9: Backfill / replay | C9: 10-year fund history, 2013+ SWIFT history, ARSIV yearly rollovers | D9: Replay from immutable landing with a separate load_id; partition exchange for bulk history | E9: 5 | F9: 3 | G9: 5 | H9: 4 | I9: 4
A11: Notes per tool
A12: Class | E12: ODI | F12: PowerCenter | G12: dbt | H12: CDP | I12: Spark
A13: S0 | E13: Only with GoldenGate JKM | F13: PowerExchange CDC / real-time option | G13: Not supported | H13: Kafka/Flink/NiFi native | I13: Structured Streaming + Kafka
A14: S1 | E14: Scheduled load plans, CDC on watermark or GG | F14: Scheduled workflows / CDC | G14: Microbatch incremental, scheduled by Automic | H14: Streaming or micro-batch | I14: Trigger-based micro-batch
A15: S2 | E15: Core use case | F15: Core use case, engine tier | G15: Core use case once landed | H15: Works, but off-Exadata | I15: Works, but off-Exadata
A16: S3 | E16: File and web-service tools | F16: Broadest connectors | G16: Needs separate ingestion | H16: NiFi | I16: Custom code
A17: S4 | E17: Set-based bulk + partition exchange | F17: Engine throughput bound | G17: full-refresh / microbatch backfill | H17: Scales out, then write back | I17: Scales out, then write back

Sheet Use-Case Fit
A1: Fit to Takasbank workloads (1-5)
A2: Workloads taken from the July 2025 DWH presentation and UG meeting notes.
A4: ID | B4: Use case | C4: Volume / behaviour | D4: ODI | E4: PowerCenter | F4: dbt | G4: CDP | H4: Spark
A5: UC1 | B5: SWIFT legal reports | C5: 2B rows / 170 GB since 2013, ~1M messages/day; collapse to ~24M one-row-per-message summary; free-text ID search; T-1. | D5: 5 | E5: 3 | F5: 5 | G5: 3 | H5: 3
A6: UC2 | B6: Fon Bilgilendirme platform | C6: ~60k fund notifications/day, recalculation 08:00-17:45 with correction files; 10-year history via CSV and web service. | D6: 4 | E6: 3 | F6: 3 | G6: 4 | H6: 3
A7: UC3 | B7: Fon islem defterleri | C7: 9M Borsa DWH fund contracts/day (deleted at source after 5 days), cleanse to ~600k, files twice a day per market to Borsa Verda. | D7: 4 | E7: 4 | F7: 2 | G7: 4 | H7: 3
A8: UC4 | B8: BISTECH SPK 13 reports | C8: Kale NOMX + Replica BIDB, after Takas UG gün sonu; replace DB_ARSIV dblink views with PUB snapshots. | D8: 5 | E8: 4 | F8: 4 | G8: 2 | H8: 2
A9: UC5 | B9: EPIAS energy settlement feeds | C9: Order/settlement files via web services, 5-10k records/day, collateral data, avans.takas table. | D9: 3 | E9: 4 | F9: 1 | G9: 5 | H9: 2
A10: UC6 | B10: Operational izleme screens (S0) | C10: Intraday current-state queries now hitting prod Kale from Team Developer / React. | D10: 2 | E10: 2 | F10: 1 | G10: 4 | H10: 3
A11: UC7 | B11: Takas positions and history | C11: ~20M derivative and non-derivative positions/day; yearly banka -> banka_old -> arsiv rollover moves into DWH partitions. | D11: 5 | E11: 3 | F11: 4 | G11: 4 | H11: 4
B12: Average fit | D12: =ROUND(AVERAGE(D5:D11),2) | E12: =ROUND(AVERAGE(E5:E11),2) | F12: =ROUND(AVERAGE(F5:F11),2) | G12: =ROUND(AVERAGE(G5:G11),2) | H12: =ROUND(AVERAGE(H5:H11),2)

Sheet TCO Drivers
A1: 5-year TCO drivers (bands, not quotes)
A2: List prices are public reference points only; Takasbank must obtain quotes. Higher band = higher cost.
A4: Driver | B4: ODI | C4: PowerCenter | D4: dbt | E4: CDP | F4: Spark
A5: Software licence (5 yr) | B5: Medium-High: list ref. USD 30k per processor on agent hosts (x86 core factor 0.5) + 22%/yr support | C5: High: quote-based; extended-support premium; migration to IPU billing within window | D5: None | E5: High: CCU + data-under-management subscription (quote-based) | F5: None
A6: CDC / real-time add-on | B6: GoldenGate per processor on capture/delivery hosts, only for S0 products (licence includes ADG entitlement) | C6: PowerExchange CDC licence | D6: External (ADG / GoldenGate) | E6: Included in Cloudera Streaming subscription; Oracle log reader still needed | F6: Kafka + Debezium (free) - operate yourself
A7: Infrastructure | B7: Low: 2 agent VMs; compute on existing Exadata | C7: Medium: integration-service servers + repository DB | D7: Low: runner VMs; compute on existing Exadata | E7: High: new multi-node cluster (storage, masters, Kafka brokers) | F7: High: new Kubernetes/YARN cluster + Kafka
A8: People (build + run) | B8: 2 data engineers + part-time ODI admin | C8: 2 ETL developers + Informatica admin | D8: 2-3 data engineers (incl. ingestion framework) + DevOps support | E8: Platform team 3-4 + 2 data engineers; 24/7 on-call | F8: 3-5 platform/data engineers; 24/7 on-call
A9: Training / hiring risk | B9: Low-Medium | C9: Medium | D9: Low-Medium | E9: High | F9: High
A10: Exit / migration cost | B10: Medium: logic in KMs/mappings, SQL is visible | C10: High: forced re-platform before 2029 | D10: Low: plain SQL in Git | E10: High | F10: Medium
A11: Overall 5-year band | B11: Medium | C11: High | D11: Low | E11: Very high | F11: High

Sheet Risks
A1: Risk register by tool
A4: Tool | B4: Risk | C4: Likelihood | D4: Impact | E4: Mitigation
A5: ODI | B5: GoldenGate operational burden if S0 products are approved | C5: Medium | D5: High | E5: Serve raw izleme from ADG standby first; GoldenGate only per product with DBA on-call agreed; monitor lag in CTL.
A6: ODI | B6: Licence scope creep (agents on more hosts, HA needs WebLogic EE) | C6: Medium | D6: Medium | E6: Fix agent topology before the PO; standalone agents with Automic-level failover instead of WebLogic cluster.
A7: ODI | B7: GUI development hides logic from code review | C7: Medium | D7: Medium | E7: ODI VCS on Git, naming standards, scenario versioning, generated-SQL review in PR.
A8: PowerCenter | B8: Product end-of-life forces a second migration | C8: High | D8: High | E8: Do not select; if ever considered, price the IDMC migration and confirm on-prem control-plane options in writing.
A9: PowerCenter | B9: Cloud control plane conflicts with data-residency rules | C9: High | D9: High | E9: Legal/compliance review of CDI-PC Secure Agent connectivity before any further evaluation.
A10: dbt | B10: Home-built ingestion framework becomes an unsupported product | C10: Medium | D10: High | E10: Keep landing minimal (external tables, PL/SQL pulls from standby), documented and owned; or pair with ODI for ingestion.
A11: dbt | B11: Oracle adapter lags dbt v2 / Fusion | C11: High | D11: Medium | E11: Pin dbt-core 1.x + dbt-oracle; track adapter roadmap; avoid features exclusive to the SaaS platform.
A12: dbt | B12: No vendor SLA for production incidents | C12: Medium | D12: Medium | E12: Third-party support contract or internal runbooks; failure surface is small because SQL runs in Oracle.
A13: CDP | B13: Second platform without a platform team | C13: High | D13: High | E13: Do not adopt for the core DWH; reconsider only with a funded streaming/AI programme and team.
A14: CDP | B14: Two copies of regulated data and two security perimeters | C14: High | D14: Medium | E14: Ranger/Atlas + KVKK classification on both sides; avoid by keeping the DWH on Exadata.
A15: Spark | B15: DIY platform with no vendor support | C15: High | D15: High | E15: Not recommended; if needed, buy commercial support and limit to non-critical analytics.
... A18: All | B18: Historical rows updated in place break incremental loads | C18: Medium | D18: High | E18: Profile change columns on the standby; fall back to SCN snapshots and hash-diff where no reliable timestamp exists.

Sheet PoC Plan
A1: Proof of concept: ODI vs dbt head-to-head on Takasbank data
A2: Run on the Kale standby and DSS, never prod Kale. PowerCenter excluded by gate G2; CDP/Spark excluded by fit.
A4: Test | B4: Name | C4: Use case | D4: What is measured | E4: Acceptance criterion | F4: ODI result | G4: dbt result
A5: T1 | B5: SWIFT bulk + delta | C5: UC1 | D5: Initial load of the 2B-row history and daily delta into the summary table; elapsed time, Exadata CPU/IO, Smart Scan offload ratio. | E5: Daily delta finishes inside the T-1 window; result matches the current Kale query for a sampled set of IDs.
A6: T2 | B6: Intraday Fon recompute | C6: UC2 | D6: Micro-batch from standby every 15 min, with a correction file mid-day. | E6: End-to-end freshness 15 min or better; corrected fund recomputed; reruns are idempotent.
A7: T3 | B7: Borsa contract capture + Verda files | C7: UC3 | D7: Land 9M contracts/day raw; cleanse; produce per-market files twice a day with manifest and hash. | E7: No lost day (5-day source retention); files byte-identical to the current output on a test day.
A8: T4 | B8: SPK report reconciliation | C8: UC4 | D8: Build 3 of the 13 SPK reports from NOMX + Replica BIDB after the gün sonu event. | E8: 100% reconciliation with the current Kale tables for the same business date.
A9: T5 | B9: Replay and backfill | C9: UC7 | D9: Replay a failed day from landing under a new load_id; backfill one year of positions. | E9: Same result as the original run; no manual data fixes.
A10: T6 | B10: Restart after failure | C10: All | D10: Kill a run mid-load. | E10: Restarts from the failed step without duplicates; operator steps documented in a runbook.
A11: T7 | B11: Lineage | C11: UC4 | D11: Trace one SPK report column back to source columns. | E11: Column-level lineage available without manual spreadsheets.
A12: T8 | B12: Automic + gün sonu event | C12: All | D12: Trigger the S2 chain from the batch-control record, not a clock. | E12: Chain starts on the event; failures alert Automic and the owner.
A13: T9 | B13: Security | C13: All | D13: Secrets handling, least-privilege accounts, TDE/VPD/redaction respected, audit of reads/exports. | E13: Security team sign-off; no data or metadata leaves the bank.
A14: T10 | B14: Promotion and CI | C14: All | D14: Promote a change DEV -> TEST -> PREPROD with automated tests. | E14: Repeatable, reviewed deployment with rollback.

Sheet Context & Requirements
A1: Takasbank context that drives the evaluation
A2: Facts from the Obsidian vault notes (meetings, presentations, topology). Not vendor claims.
A4: Topic | B4: Fact
A5: Institution | B5: Post-trade market infrastructure (clearing, CCP, settlement, custody, payments); SPK/BDDK/TCMB regulated; data cannot leave the bank.
A6: Core source | B6: Kale on the kale Exadata: ~90% of all data, ~10 TB, ~7,000 main + ~3,000 backup tables, no ERD; member tables duplicated per schema.
A7: Other sources | B7: ARSIV (banka -> banka_old -> arsiv yearly), CekDB (cheque images as CLOB), BIST Replica BIDB / Borsa DWH, FTP/CSV, EPIAS web services, possibly Postgres/MSSQL.
A8: Hardware | B8: Three Exadata (kale, sur, hisar), ~200 TB each, 77-90% disk free, sur CPU ~6-12%, hisar ~2-3% (Dec 2024 snapshot).
A9: Replicas | B9: Kale has two Data Guard replicas, one on sur; DSS and PREPROD are detached from Kale at 07:00; tvsods is a live copy on kale.
A10: Reporting | B10: Team Developer screens, React web, MicroStrategy (10-20% migrated), member terminal reports, SPK/MASAK/BDDK/Hazine reports with hour-level SLAs.
A11: Real-time demand | B11: 'Izleme' screens are near-real-time current-state views; Fon Bilgilendirme recalculates 08:00-17:45; Piyasalar UG reports performance problems.
A12: Gün sonu | B12: Manually triggered, completion by e-mail; Preprod flashback snapshots 04:00-07:00; no machine-readable completion signal.
A13: Team | B13: IZV: 1 manager + 2 MSTR developers; strong Oracle DBA/PL/SQL; no DWH/ETL experience; table knowledge sits with UG analysts.
A14: Operations | B14: No 24/7 monitoring team; DBA team considers GoldenGate fragile; Automic used as scheduler by several teams.
A15: Licences known | B15: Informatica TDM (masking) only; GoldenGate licence status disputed (Obase: exists; DBA: new); ADG status to be confirmed.
A16: Procurement | B16: Slow; any product needing a new PO delays the pilot.

Sheet Sources
A1: Sources (verified 2026-10-14)
A4: # | B4: Source | C4: URL
A5: 1 | B5: Oracle FMW Statement of Direction (14.1.2 support to 2030/2033) | C5: https://blogs.oracle.com/fusionmiddlewaresupport/oracle-fusion-middleware-statement-of-direction-is-now-available
A6: 2 | B6: What's new in ODI 14c (14.1.2.0.0) | C6: https://docs.oracle.com/en/middleware/fusion-middleware/data-integrator/14.1.2/odiad/whats-new-oracle-data-integrator.html
A7: 3 | B7: Oracle Data Integration products licensing information | C7: https://docs.oracle.com/en/middleware/fusion-middleware/fmwlc/data-integration-products.html
A8: 4 | B8: ODI licensing in 2026 (list price reference) | C8: https://redresscompliance.com/oracle-data-integrator-licensing
A9: 5 | B9: ODI GoldenGate JKM documentation | C9: https://docs.oracle.com/middleware/odi121301/odi/develop-connectivity-km/ogg.htm
A10: 6 | B10: Oracle GoldenGate licensing (includes ADG/XStream entitlement) | C10: https://docs.oracle.com/en/middleware/goldengate/core/21.3/ogglc/oracle-goldengate-licensing-guide.pdf
A11: 7 | B11: Informatica community: PowerCenter 10.5.x end of support | C11: https://network.informatica.com/s/question/0D5VM00000m2Kag0AE/informatica-1056
A12: 8 | B12: Informatica: PowerCenter EoS does not apply to CDI-PC | C12: https://knowledge.informatica.com/s/article/000245032?language=en_US
A13: 9 | B13: CDI-PC April 2026 What's New (mandatory cloud-managed updates) | C13: https://docs.informatica.com/content/dam/source/GUID-1/GUID-1A371312-AE91-482A-ABF1-D612D25A99D6/19/en/CDIPC_April2026_WhatSNew_en.pdf
A14: 10 | B14: Salesforce completes acquisition of Informatica (18 Nov 2025) | C14: https://investor.salesforce.com/news/news-details/2025/Salesforce-Completes-Acquisition-of-Informatica/default.aspx
A15: 11 | B15: Fivetran + dbt Labs complete merger (1 Jun 2026) | C15: https://www.getdbt.com/blog/fivetran-dbt-labs-complete-merger-to-create-the-data-infrastructure-for-trusted-ai-agents
A16: 12 | B16: dbt licensing | C16: https://docs.getdbt.com/docs/dbt-licensing
... A26: 22 | B26: Oracle GoldenGate Free FAQ (limits) | C26: https://docs.oracle.com/en/middleware/goldengate/free/23/uggfe/frequently-asked-questions.html
